quizzable/__init__.py
quizzable/exceptions.py
tests/__init__.py
tests/test_classes.py
tests/test_functions.py
quizzable-1.1.0.dist-info/LICENSE
quizzable-1.1.0.dist-info/METADATA
quizzable-1.1.0.dist-info/WHEEL
quizzable-1.1.0.dist-info/top_level.txt
quizzable-1.1.0.dist-info/RECORD
