Metadata-Version: 2.1
Name: quizzable
Version: 1.1.0
Summary: Education with Python.
Home-page: https://github.com/balusulapalemsaikoushik/quizzable/
Author: Sai Koushik Balusulapalem
License: MIT License
Project-URL: Bug Tracker, https://github.com/balusulapalemsaikoushik/quizzable/issues
Project-URL: Documentation, https://github.com/balusulapalemsaikoushik/quizzable/blob/main/README.md
Keywords: education,app,quiz,learn,backend
Classifier: Intended Audience :: Developers
Classifier: License :: OSI Approved :: MIT License
Classifier: Operating System :: Microsoft :: Windows
Classifier: Operating System :: MacOS
Classifier: Operating System :: POSIX :: Linux
Classifier: Programming Language :: Python :: 3
Classifier: Programming Language :: Python :: 3.9
Classifier: Programming Language :: Python :: 3.10
Classifier: Programming Language :: Python :: 3.11
Classifier: Programming Language :: Python :: 3.12
License-File: LICENSE
